{
  "TDesign Button 按钮": {
    "prefix": "td-button",
    "body": [
      "<t-button theme='primary' size='medium'>${3:填充按钮}</t-button>"
    ],
    "description": "TDesign Button 组件"
  },
  "TDesign Divider 分割线": {
    "prefix": "td-divider",
    "body": [
      "<t-divider />"
    ],
    "description": "TDesign Divider 组件"
  },
  "TDesign Fab 悬浮按钮": {
    "prefix": "td-fab",
    "body": [
      "<t-fab icon=\"add\" bind:click=\"handleClick\" text=\"增加\"></t-fab>"
    ],
    "description": "TDesign Fab 组件"
  },
  "TDesign Icon 图标": {
    "prefix": "td-icon",
    "body": [
      "<t-icon name=\"${1}\" size=\"48rpx\" color=\"\" />"
    ],
    "description": "TDesign Icon 组件"
  },
  "TDesign Layout 布局": {
    "prefix": "td-layout",
    "body": [
      "<t-row>",
      "  <t-col span=\"8\" t-class=\"\">col-8</t-col>",
      "  <t-col span=\"8\" t-class=\"\">col-8</t-col>",
      "  <t-col span=\"8\" t-class=\"\">col-8</t-col>",
      "</t-row>"
    ],
    "description": "TDesign Layout 组件"
  },
  "TDesign Row 行": {
    "prefix": "td-row",
    "body": [
      "<t-row>",
      "${1}",
      "</t-row>"
    ],
    "description": "TDesign Row 组件"
  },
  "TDesign Col 列": {
    "prefix": "td-col",
    "body": [
      "<t-col span=\"8\" t-class=\"\">col-8</t-col>"
    ],
    "description": "TDesign Col 组件"
  },
  "TDesign Link 链接": {
    "prefix": "td-link",
    "body": [
      "<t-link size=\"small\" theme=\"primary\" content=\"跳转链接\" hover />"
    ],
    "description": "TDesign Link 组件"
  },
  "TDesign BackTop 回到顶部": {
    "prefix": "td-back-top",
    "body": [
      "<t-back-top",
      "  theme=\"round\"",
      "  text=\"顶部\"",
      "  scroll-top=\"{{{ type: Number, value: 0 }}}\"",
      "  bind:to-top=\"onToTop\"",
      "></t-back-top>"
    ],
    "description": "TDesign BackTop 组件"
  },
  "TDesign Drawer 抽屉": {
    "prefix": "td-drawer",
    "body": [
      "<t-drawer",
      "  visible=\"{{visible}}\"",
      "  placement=\"left\"",
      "  items=\"{{[]}}\"",
      "  usingCustomNavbar",
      "  bind:overlay-click=\"overlayClick\"",
      "  bind:item-click=\"itemClick\"",
      "></t-drawer>"
    ],
    "description": "TDesign Drawer 组件"
  },
  "TDesign Indexes 索引": {
    "prefix": "td-indexes",
    "body": [
      "<t-indexes bind:select=\"onSelect\" index-list=\"{{indexList}}\" sticky-offset=\"{{stickyOffset}}\">",
      "  <block wx:for=\"{{list}}\" wx:key=\"index\">",
      "    <t-indexes-anchor index=\"{{item.index}}\" />",
      "    <t-cell-group>",
      "      <t-cell wx:for=\"{{item.children}}\" wx:key=\"city\" wx:for-item=\"city\" title=\"{{city}}\" aria-role=\"button\" />",
      "    </t-cell-group>",
      "  </block>",
      "</t-indexes>"
    ],
    "description": "TDesign Indexes 组件"
  },
  "TDesign Navbar 导航栏": {
    "prefix": "td-navbar",
    "body": [
      "<t-navbar",
      "  t-class-placeholder=\"t-navbar-placeholder\"",
      "  t-class-content=\"t-navbar-content\"",
      "  class=\"block\"",
      "  title=\"标题文字\"",
      "  left-arrow",
      "  bind:go-back=\"handleBack\"",
      "/>"
    ],
    "description": "TDesign Navbar 组件"
  },
  "TDesign SideBar 侧边栏": {
    "prefix": "td-side-bar",
    "body": [
      "<view class=\"side-bar-wrapper\" style=\"height: calc(100vh - {{navbarHeight}}px)\">",
      "  <t-side-bar value=\"{{sideBarIndex}}\" bind:change=\"onSideBarChange\">",
      "    <t-side-bar-item",
      "      wx:for=\"{{categories}}\"",
      "      wx:key=\"label\"",
      "      value=\"{{item.value || index}}\"",
      "      label=\"{{item.label}}\"",
      "      badge-props=\"{{item.badgeProps}}\"",
      "    />",
      "  </t-side-bar>",
      "  <scroll-view class=\"content\" scroll-y scroll-with-animation scroll-top=\"{{scrollTop}}\" bind:scroll=\"onScroll\">",
      "    <view wx:for=\"{{categories}}\" wx:key=\"index\" class=\"section\">",
      "      <view class=\"title\">{{item.title || item.label}}</view>",
      "    </view>",
      "  </scroll-view>",
      "</view>"
    ],
    "description": "TDesign SideBar 组件"
  },
  "TDesign Steps 步骤条": {
    "prefix": "td-steps",
    "body": [
      "<t-steps current=\"{{first}}\" bind:change=\"onFirstChange\">",
      "  <t-step-item wx:for=\"{{list}}\" wx:key=\"index\" title=\"{{item.title)}}\" content=\"辅助信息\" />",
      "</t-steps>"
    ],
    "description": "TDesign Steps 组件"
  },
  "TDesign TabBar 标签栏": {
    "prefix": "td-tab-bar",
    "body": [
      "<t-tab-bar t-class=\"t-tab-bar\" value=\"{{value}}\" bindchange=\"onChange\" theme=\"tag\" split=\"{{false}}\">",
      "  <t-tab-bar-item wx:for=\"{{list}}\" wx:key=\"index\" value=\"{{item.value}}\"> {{item.label}} </t-tab-bar-item>",
      "</t-tab-bar>"
    ],
    "description": "TDesign TabBar 组件"
  },
  "TDesign Tabs 选项卡": {
    "prefix": "td-tabs",
    "body": [
      "<t-tabs value=\"{{0}}\" bind:change=\"onTabsChange\" bind:click=\"onTabsClick\" t-class=\"custom-tabs\">",
      "  <t-tab-panel label=\"选项\" value=\"0\" />",
      "  <t-tab-panel label=\"选项\" value=\"1\" />",
      "  <t-tab-panel label=\"上限六个文字\" value=\"2\" />",
      "</t-tabs>"
    ],
    "description": "TDesign Tabs 组件"
  },
  "TDesign Calendar 日历": {
    "prefix": "td-calendar",
    "body": [
      "<t-calendar visible=\"{{visible}}\" bind:confirm=\"handleConfirm\" bind:close=\"onClose\" />"
    ],
    "description": "TDesign Calendar 组件"
  },
  "TDesign Calendar:range 日历": {
    "prefix": "td-calendar:range",
    "body": [
      "<t-calendar visible=\"{{visible}}\" bind:confirm=\"handleConfirm\" type=\"range\" />"
    ],
    "description": "TDesign Calendar 组件"
  },
  "TDesign Cascader 级联选择器": {
    "prefix": "td-cascader",
    "body": [
      "<t-cascader",
      "  visible=\"{{visible}}\"",
      "  value=\"{{value}}\"",
      "  options=\"{{options}}\"",
      "  title=\"请选择地址\"",
      "  bind:change=\"onChange\"",
      "  bind:pick=\"onPick\"",
      "/>"
    ],
    "description": "TDesign Cascader 组件"
  },
  "TDesign Checkbox 多选框": {
    "prefix": "td-checkbox",
    "body": [
      "<t-checkbox value=\"{{checkbox1}}\" label=\"多选\" />"
    ],
    "description": "TDesign Checkbox 组件"
  },
  "TDesign Checkbox-group 多选框": {
    "prefix": "td-checkbox-group",
    "body": [
      "<t-checkbox-group value=\"{{current}}\" bind:change=\"handleGroupChange\" options=\"{{options}}\" />"
    ],
    "description": "TDesign Checkbox 组件"
  },
  "TDesign DateTimePicker:date 时间选择器": {
    "prefix": "td-date-time-picker:date",
    "body": [
      "<t-date-time-picker",
      "  title=\"选择日期\"",
      "  visible=\"{{dateVisible}}\"",
      "  mode=\"date\"",
      "  value=\"{{date}}\"",
      "  format=\"YYYY-MM-DD\"",
      "  bindchange=\"onConfirm\"",
      "  bindpick=\"onColumnChange\"",
      "  bindcancel=\"hidePicker\"",
      "  start=\"{{start}}\"",
      "  end=\"{{end}}\"",
      "/>"
    ],
    "description": "TDesign DateTimePicker 组件"
  },
  "TDesign DateTimePicker:second 时间选择器": {
    "prefix": "td-date-time-picker:second",
    "body": [
      "<t-date-time-picker",
      "  title=\"选择日期和时间\"",
      "  visible=\"{{datetimeVisible}}\"",
      "  mode=\"second\"",
      "  value=\"{{datetime}}\"",
      "  format=\"YYYY-MM-DD HH:mm:ss\"",
      "  bindchange=\"onConfirm\"",
      "  bindpick=\"onColumnChange\"",
      "  bindcancel=\"hidePicker\"",
      "/>"
    ],
    "description": "TDesign DateTimePicker 组件"
  },
  "TDesign Input 输入框": {
    "prefix": "td-input",
    "body": [
      "<t-input label=\"标签文字\" placeholder=\"请输入文字\" clearable />"
    ],
    "description": "TDesign Input 组件"
  },
  "TDesign Input:password 输入框": {
    "prefix": "td-input:password",
    "body": [
      "<t-input label=\"输入密码\" type=\"password\" value=\"{{textPassword}}\" clearable />"
    ],
    "description": "TDesign Input 组件"
  },
  "TDesign Input:验证码 输入框": {
    "prefix": "td-input:code",
    "body": [
      "<t-input placeholder=\"输入验证码\" label=\"验证码\">",
      "  <view slot=\"suffix\" class=\"suffix\">",
      "    <view class=\"suffix--line\"></view>",
      "    <image",
      "      class=\"image\"",
      "      src=\"https://wwcdn.weixin.qq.com/node/wework/images/202010241547.ac6876be9c.png\"",
      "      mode=\"heightFix\"",
      "      aria-role=\"img\"",
      "      aria-label=\"验证码\"",
      "    />",
      "  </view>",
      "</t-input>"
    ],
    "description": "TDesign Input 组件"
  },
  "TDesign Input:手机号 输入框": {
    "prefix": "td-input:phone",
    "body": [
      "<t-input",
      "  label=\"手机号\"",
      "  placeholder=\"输入手机号码\"",
      "  value=\"{{phoneNumber}}\"",
      "  type=\"number\"",
      "  tips=\"{{phoneError ? '手机号输入不正确' : ''}}\"",
      "  bindchange=\"onPhoneInput\"",
      ">",
      "  <view slot=\"suffix\" style=\"display: flex; align-items: center\">",
      "    <view class=\"suffix--line\"></view>",
      "    <view class=\"verify\" aria-role=\"button\"> 发送验证码 </view>",
      "  </view>",
      "</t-input>"
    ],
    "description": "TDesign Input 组件"
  },
  "TDesign Input:价格 输入框": {
    "prefix": "td-input:price",
    "body": [
      "<t-input",
      "  label=\"价格\"",
      "  value=\"{{priceNumber}}\"",
      "  placeholder=\"0.00\"",
      "  suffix=\"元\"",
      "  align=\"right\"",
      "  type=\"number\"",
      "  bindchange=\"onPriceInput\"",
      "  tips=\"{{priceError ? '请输入正确的价格' : ''}}\"",
      "  t-class-tips=\"tips\"",
      "/>"
    ],
    "description": "TDesign Input 组件"
  },
  "TDesign Input:数量 输入框": {
    "prefix": "td-input:number",
    "body": [
      "<t-input label=\"数量\" value=\"{{number}}\" placeholder=\"填写个数\" suffix=\"个\" align=\"right\" type=\"number\" />"
    ],
    "description": "TDesign Input 组件"
  },
  "TDesign Picker 选择器": {
    "prefix": "td-picker",
    "body": [
      "<t-picker",
      "  visible=\"{{areaVisible}}\"",
      "  value=\"{{areaValue}}\"",
      "  title=\"选择地区\"",
      "  cancelBtn=\"取消\"",
      "  confirmBtn=\"确认\"",
      "  usingCustomNavbar",
      "  bindchange=\"onPickerChange\"",
      "  bindpick=\"onColumnChange\"",
      "  bindcancel=\"onPickerCancel\"",
      ">",
      "  <t-picker-item options=\"{{provinces}}\"></t-picker-item>",
      "  <t-picker-item options=\"{{cities}}\"></t-picker-item>",
      "  <t-picker-item options=\"{{counties}}\"></t-picker-item>",
      "</t-picker>"
    ],
    "description": "TDesign Picker 组件"
  },
  "TDesign Radio 单选框": {
    "prefix": "td-radio",
    "body": [
      "<t-radio checked=\"{{true}}\" allow-uncheck label=\"单选\" />"
    ],
    "description": "TDesign Radio 组件"
  },
  "TDesign Radio-group 单选框": {
    "prefix": "td-radio-group",
    "body": [
      "<t-radio-group bind:change=\"onChange\" allow-uncheck value=\"{{current}}\" options=\"{{options}}\" />"
    ],
    "description": "TDesign Radio 组件"
  },
  "TDesign Rate 评分": {
    "prefix": "td-rate",
    "body": [
      "<t-rate value=\"{{value}}\" bind:change=\"onChange\" />"
    ],
    "description": "TDesign Rate 组件"
  },
  "TDesign Search 搜索框": {
    "prefix": "td-search",
    "body": [
      "<t-search placeholder=\"搜索预设文案\" bind:change=\"onChangeValue\" />"
    ],
    "description": "TDesign Search 组件"
  },
  "TDesign Slider 滑动选择器": {
    "prefix": "td-slider",
    "body": [
      "<t-slider value=\"{{value}}\" label=\"{{value}}\" bind:change=\"handleChange\" />"
    ],
    "description": "TDesign Slider 组件"
  },
  "TDesign Stepper 步进器": {
    "prefix": "td-stepper",
    "body": [
      "<t-stepper value=\"{{value}}\" theme=\"filled\" min=\"0\" max=\"999\" />"
    ],
    "description": "TDesign Stepper 组件"
  },
  "TDesign Switch 开关": {
    "prefix": "td-switch",
    "body": [
      "<t-switch value=\"{{true}}\" bindchange=\"handleChange\" />"
    ],
    "description": "TDesign Switch 组件"
  },
  "TDesign Textarea 多行文本框": {
    "prefix": "td-textarea",
    "body": [
      "<t-textarea t-class=\"external-class\" placeholder=\"请输入文字\" bindchange=\"handleChange\" disableDefaultPadding=\"{{true}}\" />"
    ],
    "description": "TDesign Textarea 组件"
  },
  "TDesign TreeSelect 树形选择": {
    "prefix": "td-tree-select",
    "body": [
      "<t-tree-select options=\"{{options}}\" value=\"{{value}}\" bind:change=\"onChange\" />"
    ],
    "description": "TDesign TreeSelect 组件"
  },
  "TDesign TreeSelect:multiple 树形选择": {
    "prefix": "td-tree-select:multiple",
    "body": [
      "<t-tree-select options=\"{{options}}\" value=\"{{value}}\" multiple bind:change=\"onChange\" />"
    ],
    "description": "TDesign TreeSelect 组件"
  },
  "TDesign Upload 上传": {
    "prefix": "td-upload",
    "body": [
      "<t-upload",
      "  mediaType=\"{{['video','image']}}\"",
      "  max=\"{{1}}\"",
      "  files=\"{{fileList}}\"",
      "  bind:add=\"handleAdd\"",
      "  bind:remove=\"handleRemove\"",
      ">",
      "</t-upload>"
    ],
    "description": "TDesign Upload 组件"
  },
  "TDesign Upload:多选 上传": {
    "prefix": "td-upload:multiple",
    "body": [
      "<t-upload",
      "  media-type=\"{{['video','image']}}\"",
      "  max=\"{{3}}\"",
      "  files=\"{{originFiles}}\"",
      "  gridConfig=\"{{gridConfig}}\"",
      "  bind:success=\"handleSuccess\"",
      "  bind:remove=\"handleRemove\"",
      "  bind:click=\"handleClick\"",
      "  bind:sort-end=\"handleSortEnd\"",
      "/>"
    ],
    "description": "TDesign Upload 组件"
  },
  "TDesign Avatar 头像": {
    "prefix": "td-avatar",
    "body": [
      "<t-avatar class=\"avatar-example\" shape=\"${1|circle,round|}\" image=\"{{image}}\" size=\"medium\" />"
    ],
    "description": "TDesign Avatar 组件"
  },
  "TDesign Avatar-group 头像": {
    "prefix": "td-avatar-group",
    "body": [
      "<t-avatar-group max=\"5\" collapseAvatar=\"+5\">",
      "  <t-avatar wx:for=\"{{pics}}\" wx:for-item=\"pic\" wx:key=\"index\" image=\"{{pic}}\" />",
      "</t-avatar-group>"
    ],
    "description": "TDesign Avatar 组件"
  },
  "TDesign Badge:红点 徽标": {
    "prefix": "td-badge:dot",
    "body": [
      "<t-badge dot class=\"\" content=\"消息\" />"
    ],
    "description": "TDesign Badge 组件"
  },
  "TDesign Badge:数字 徽标": {
    "prefix": "td-badge:count",
    "body": [
      "<t-badge count=\"8\" content=\"消息\" offset=\"{{ [4] }}\" class=\"\" />"
    ],
    "description": "TDesign Badge 组件"
  },
  "TDesign Cell 单元格": {
    "prefix": "td-cell",
    "body": [
      "<t-cell title=\"单行标题\" note=\"辅助信息\" description=\"\" hover arrow />"
    ],
    "description": "TDesign Cell 组件"
  },
  "TDesign Cell:switch 单元格": {
    "prefix": "td-cell:switch",
    "body": [
      "<t-cell title=\"单行标题\" hover>",
      "  <t-switch value=\"{{true}}\" slot=\"note\" />",
      "</t-cell>"
    ],
    "description": "TDesign Cell 组件"
  },
  "TDesign Cell-group 单元格": {
    "prefix": "td-cell-group",
    "body": [
      "<t-cell-group theme=\"card\">",
      "  <t-cell title=\"单行标题\" leftIcon=\"service\" hover arrow />",
      "  <t-cell title=\"单行标题\" leftIcon=\"internet\" hover arrow />",
      "  <t-cell title=\"单行标题\" leftIcon=\"lock-on\" hover arrow />",
      "</t-cell-group>"
    ],
    "description": "TDesign Cell 组件"
  },
  "TDesign Collapse 折叠面板": {
    "prefix": "td-collapse",
    "body": [
      "<view class=\"\">",
      "  <t-collapse value=\"{{activeValues}}\" bind:change=\"handleChange\">",
      "    <t-collapse-panel header=\"折叠面板标题\" value=\"{{0}}\" expandIcon>",
      "      此处可自定义内容此处可自定义内容此处可自定义内容此处可自定义内容",
      "    </t-collapse-panel>",
      "  </t-collapse>",
      "</view>"
    ],
    "description": "TDesign Collapse 组件"
  },
  "TDesign CountDown 倒计时": {
    "prefix": "td-count-down",
    "body": [
      "<t-count-down time=\"{{ time }}\" size=\"small\" />"
    ],
    "description": "TDesign CountDown 组件"
  },
  "TDesign CountDown:millisecond 倒计时": {
    "prefix": "td-count-down:millisecond",
    "body": [
      "<t-count-down format\"HH:mm:ss:SSS\" time=\"{{ time }}\" millisecond />"
    ],
    "description": "TDesign CountDown 组件"
  },
  "TDesign CountDown:theme 倒计时": {
    "prefix": "td-count-down:theme",
    "body": [
      "<t-count-down content=\"default\" time=\"{{ time }}\" theme=\"${1|default,round,square|}\"> </t-count-down>"
    ],
    "description": "TDesign CountDown 组件"
  },
  "TDesign CountDown:unit 倒计时": {
    "prefix": "td-count-down:unit",
    "body": [
      "<t-count-down content=\"default\" time=\"{{ time }}\" splitWithUnit theme=\"round\" />"
    ],
    "description": "TDesign CountDown 组件"
  },
  "TDesign Empty 空状态": {
    "prefix": "td-empty",
    "body": [
      "<t-empty icon=\"info-circle-filled\" description=\"描述文字\" />"
    ],
    "description": "TDesign Empty 组件"
  },
  "TDesign Footer 页脚": {
    "prefix": "td-footer",
    "body": [
      "<t-footer text=\"{{text}}\" links=\"{{[]}}\" logo=\"{{{}}}\"></t-footer>"
    ],
    "description": "TDesign Footer 组件"
  },
  "TDesign Grid 宫格": {
    "prefix": "td-grid",
    "body": [
      "<t-grid class=\"block\">",
      "  <t-grid-item text=\"标题文字\" description=\"描述文字\" image=\"{{img1}}\" />",
      "  <t-grid-item text=\"标题文字\" image=\"{{img2}}\" />",
      "  <t-grid-item text=\"标题文字\" image=\"{{img3}}\" />",
      "  <t-grid-item text=\"最多五个字\" image=\"{{img1}}\" />",
      "</t-grid>"
    ],
    "description": "TDesign Grid 组件"
  },
  "TDesign Image 图片": {
    "prefix": "td-image",
    "body": [
      "<t-image src=\"{{imageSrc}}\" mode=\"${1|scaleToFill,aspectFit,aspectFill,widthFix,heightFix|}\" width=\"72\" height=\"72\" />"
    ],
    "description": "TDesign Image 组件"
  },
  "TDesign ImageViewer 图片预览": {
    "prefix": "td-image-viewer",
    "body": [
      "<t-image-viewer",
      "  usingCustomNavbar",
      "  deleteBtn=\"{{deleteBtn}}\"",
      "  closeBtn=\"{{closeBtn}}\"",
      "  showIndex=\"{{showIndex}}\"",
      "  visible=\"{{visible}}\"",
      "  images=\"{{images}}\"",
      "  bind:change=\"onChange\"",
      "  bind:delete=\"onDelete\"",
      "  bind:close=\"onClose\"",
      "></t-image-viewer>"
    ],
    "description": "TDesign ImageViewer 组件"
  },
  "TDesign Progress 进度条": {
    "prefix": "td-progress",
    "body": [
      "<t-progress theme=\"plump\" percentage=\"80\" />"
    ],
    "description": "TDesign Progress 组件"
  },
  "TDesign Progress:theme 进度条": {
    "prefix": "td-progress:theme",
    "body": [
      "<t-progress theme=\"${1|line,plump,circle|}\" percentage=\"30\" trackColor=\"\" color=\"\" />"
    ],
    "description": "TDesign Progress 组件"
  },
  "TDesign Progress:status 进度条": {
    "prefix": "td-progress:status",
    "body": [
      "<t-progress theme=\"plump\" percentage=\"88\" status=\"${1|warning,error,success,active|}\" color=\"\"/>"
    ],
    "description": "TDesign Progress 组件"
  },
  "TDesign Result 结果": {
    "prefix": "td-result",
    "body": [
      "<t-result theme=\"${1|default,success,warning,error|}\" title=\"状态\" description=\"\" />"
    ],
    "description": "TDesign Result 组件"
  },
  "TDesign Skeleton 骨架屏": {
    "prefix": "td-skeleton",
    "body": [
      "<t-skeleton theme=\"${1|avatar,image,text,paragraph|}\" animation=\"${2|gradient,flashed|}\" loading></t-skeleton>"
    ],
    "description": "TDesign Skeleton 组件"
  },
  "TDesign Skeleton:rowCol 骨架屏": {
    "prefix": "td-skeleton:rowCol",
    "body": [
      "<t-skeleton class=\"col-content\" rowCol=\"{{rowColsContent}}\" loading></t-skeleton>"
    ],
    "description": "TDesign Skeleton 组件"
  },
  "TDesign Sticky 吸顶": {
    "prefix": "td-sticky",
    "body": [
      "<t-sticky offset-top=\"{{navbarHeight}}\">",
      "  <t-button size=\"large\" theme=\"primary\" t-class=\"\">基础吸顶</t-button>",
      "</t-sticky>"
    ],
    "description": "TDesign Sticky 组件"
  },
  "TDesign Swiper 轮播图": {
    "prefix": "td-swiper",
    "body": [
      "<t-swiper",
      "  current=\"{{current}}\"",
      "  autoplay=\"{{autoplay}}\"",
      "  duration=\"{{duration}}\"",
      "  interval=\"{{interval}}\"",
      "  navigation=\"{{ { type: ${1|'dots','dots-bar'} } }}\"",
      "  list=\"{{swiperList}}\"",
      "  bind:click=\"onTap\"",
      "  bind:change=\"onChange\"",
      "  bind:image-load=\"onImageLoad\"",
      ">",
      "</t-swiper>"
    ],
    "description": "TDesign Swiper 组件"
  },
  "TDesign Swiper:fraction 轮播图": {
    "prefix": "td-swiper:fraction",
    "body": [
      "<t-swiper",
      "  current=\"{{current}}\"",
      "  autoplay=\"{{autoplay}}\"",
      "  duration=\"{{duration}}\"",
      "  interval=\"{{interval}}\"",
      "  navigation=\"{{ { type: 'fraction'} }}\"",
      "  list=\"{{swiperList}}\"",
      "  paginationPosition=\"{{'bottom-right'}}\"",
      "  bind:click=\"onTap\"",
      "  bind:change=\"onChange\"",
      "  bind:image-load=\"onImageLoad\"",
      ">",
      "</t-swiper>"
    ],
    "description": "TDesign Swiper 组件"
  },
  "TDesign Swiper:controls 轮播图": {
    "prefix": "td-swiper:controls",
    "body": [
      "<t-swiper",
      "  current=\"{{current}}\"",
      "  autoplay=\"{{autoplay}}\"",
      "  duration=\"{{duration}}\"",
      "  interval=\"{{interval}}\"",
      "  navigation=\"{{ { type: '', showControls: true } } }}\"",
      "  list=\"{{swiperList}}\"",
      "  loop=\"{{false}}\"",
      "  bind:click=\"onTap\"",
      "  bind:change=\"onChange\"",
      "  bind:image-load=\"onImageLoad\"",
      ">",
      "</t-swiper>"
    ],
    "description": "TDesign Swiper 组件"
  },
  "TDesign Swiper:cards 轮播图": {
    "prefix": "td-swiper:cards",
    "body": [
      "<t-swiper",
      "  current=\"{{current}}\"",
      "  autoplay=\"{{autoplay}}\"",
      "  duration=\"{{duration}}\"",
      "  interval=\"{{interval}}\"",
      "  bindchange=\"onChange\"",
      "  navigation=\"{{ { type: 'dots' } }}\"",
      "  list=\"{{swiperList}}\"",
      "  image-props=\"{{ { shape: 'round' } }}\"",
      "  previousMargin=\"34px\"",
      "  nextMargin=\"34px\"",
      "  t-class-nav=\"card-theme-nav\"",
      "/>"
    ],
    "description": "TDesign Swiper 组件"
  },
  "TDesign Swiper:vertical 轮播图": {
    "prefix": "td-swiper:vertical",
    "body": [
      "<t-swiper",
      "  current=\"{{1}}\"",
      "  autoplay=\"{{autoplay}}\"",
      "  duration=\"{{duration}}\"",
      "  interval=\"{{interval}}\"",
      "  navigation=\"{{ { type: 'dots-bar' } }}\"",
      "  direction=\"vertical\"",
      "  paginationPosition=\"{{ 'right' }}\"",
      "  list=\"{{swiperList}}\"",
      ">",
      "</t-swiper>"
    ],
    "description": "TDesign Swiper 组件"
  },
  "TDesign Tag 标签": {
    "prefix": "td-tag",
    "body": [
      "<t-tag class=\"\"",
      "  variant=\"${1|light,outline|}\"",
      "  shape=\"${2|round,mark|}\"",
      "  size=\"${3|small,medium,large,extra-large|}\"",
      "  max-width=\"{{130}}\"",
      "  icon=\"\"",
      "  closeable=\"{{true}}\"",
      ">",
      "标签文字",
      "</t-tag>"
    ],
    "description": "TDesign Tag 组件"
  },
  "TDesign Tag:theme 标签": {
    "prefix": "td-tag:theme",
    "body": [
      "<t-tag class=\"\" variant=\"light\" theme=\"${1|default,primary,warning,danger,success|}\">主题</t-tag>"
    ],
    "description": "TDesign Tag 组件"
  },
  "TDesign Tag-check 标签": {
    "prefix": "td-check-tag",
    "body": [
      "<t-check-tag",
      "  class=\"\"",
      "  checked=\"{{true}}\"",
      "  size=\"large\"",
      "  variant=\"${1|dark,light,outline,light-outline|}\"",
      "  content=\"{{ ['已选中态', '未选中态'] }}\"",
      "/>"
    ],
    "description": "TDesign Tag 组件"
  },
  "TDesign ActionSheet 动作面板": {
    "prefix": "td-action-sheet",
    "body": [
      "<t-action-sheet id=\"t-action-sheet\" usingCustomNavbar bind:selected=\"handleSelected\" />"
    ],
    "description": "TDesign ActionSheet 组件"
  },
  "TDesign Dialog:confirm 对话框": {
    "prefix": "td-dialog:confirm",
    "body": [
      "<t-dialog",
      "  visible=\"{{showTextAndTitle}}\"",
      "  title=\"对话框标题\"",
      "  content=\"告知当前状态、信息和解决方法，等内容。描述文案尽可能控制在三行内\"",
      "  confirm-btn=\"{{ { content: '知道了', variant: 'base' }}\"",
      "  bind:confirm=\"closeDialog\"",
      "/>"
    ],
    "description": "TDesign Dialog 组件"
  },
  "TDesign Dialog:confirm,cancel 对话框": {
    "prefix": "td-dialog:confirm,cancel",
    "body": [
      "<t-dialog",
      "  visible=\"{{showTextAndTitle}}\"",
      "  title=\"对话框标题\"",
      "  content=\"告知当前状态、信息和解决方法，等内容。描述文案尽可能控制在三行内\"",
      "  confirm-btn=\"{{ { content: '确定', variant: 'base' }}\"",
      "  cancel-btn=\"取消\"",
      "  bind:confirm=\"closeDialog\"",
      "  bind:cancel=\"closeDialog\"",
      "/>"
    ],
    "description": "TDesign Dialog 组件"
  },
  "TDesign Dialog:input 对话框": {
    "prefix": "td-dialog:input",
    "body": [
      "<t-dialog",
      "  visible=\"{{showTextAndTitleWithInput}}\"",
      "  title=\"带输入框对话框\"",
      "  content=\"告知当前状态、信息和解决方法，等内容。描述文案尽可能控制在三行内\"",
      "  confirm-btn=\"确定\"",
      "  cancel-btn=\"取消\"",
      "  bind:confirm=\"closeDialog\"",
      "  bind:cancel=\"closeDialog\"",
      ">",
      "  <t-input",
      "    borderless",
      "    class=\"dialog-input\"",
      "    clearable",
      "    slot=\"content\"",
      "    placeholder=\"输入12文案\"",
      "    placeholder-class=\"placeholder\"",
      "  />",
      "</t-dialog>"
    ],
    "description": "TDesign Dialog 组件"
  },
  "TDesign Dialog:image 对话框": {
    "prefix": "td-dialog:image",
    "body": [
      "<t-dialog",
      "  visible=\"{{imageOnTop}}\"",
      "  title=\"带输入框对话框\"",
      "  content=\"告知当前状态、信息和解决方法，等内容。描述文案尽可能控制在三行内\"",
      "  confirm-btn=\"{{ {content: '确定', variant: 'base' } }}\"",
      "  cancel-btn=\"取消\"",
      "  bind:confirm=\"closeDialog\"",
      "  bind:cancel=\"closeDialog\"",
      ">",
      "  <t-image slot=\"${1|top,middle|}\" t-class=\"dialog-image\" src=\"https://tdesign.gtimg.com/mobile/demos/dialog1.png\" />",
      "</t-dialog>"
    ],
    "description": "TDesign Dialog 组件"
  },
  "TDesign Dialog 对话框": {
    "prefix": "td-dialog",
    "body": [
      "<t-dialog id=\"t-dialog\" />"
    ],
    "description": "TDesign Dialog 组件"
  },
  "TDesign DropdownMenu 下拉菜单": {
    "prefix": "td-dropdown-menu",
    "body": [
      "<t-dropdown-menu",
      "  <t-dropdown-item options=\"{{product.options}}\" value=\"{{product.value}}\" bindchange=\"onChange\" />",
      "  <t-dropdown-item options=\"{{sorter.options}}\" value=\"{{sorter.value}}\" />",
      "</t-dropdown-menu>"
    ],
    "description": "TDesign DropdownMenu 组件"
  },
  "TDesign DropdownMenu:optionsColumns 下拉菜单": {
    "prefix": "td-dropdown-menu:optionsColumns",
    "body": [
      "<t-dropdown-menu>",
      "  <t-dropdown-item",
      "    label=\"单列多选\"",
      "    options=\"{{multipleSelect.options}}\"",
      "    value=\"{{multipleSelect.value}}\"",
      "    bindchange=\"handleMultipleSelect\"",
      "    multiple",
      "  />",
      "  <t-dropdown-item",
      "    label=\"双列多选\"",
      "    optionsColumns=\"2\"",
      "    options=\"{{doubleColumnsOptions}}\"",
      "    defaultValue=\"{{['option_1', 'option_2']}}\"",
      "    multiple",
      "  />",
      "  <t-dropdown-item",
      "    label=\"三列多选\"",
      "    optionsColumns=\"3\"",
      "    options=\"{{tripleColumnsOptions}}\"",
      "    defaultValue=\"{{['option_1', 'option_2', 'option_3']}}\"",
      "    multiple",
      "  />",
      "</t-dropdown-menu>"
    ],
    "description": "TDesign DropdownMenu 组件"
  },
  "TDesign DropdownMenu:tree 下拉菜单": {
    "prefix": "td-dropdown-menu:tree",
    "body": [
      "<t-dropdown-menu>",
      "  <t-dropdown-item",
      "    label=\"树形双列\"",
      "    optionsLayout=\"tree\"",
      "    options=\"{{doubleColumnsTree.options}}\"",
      "    value=\"{{doubleColumnsTree.value}}\"",
      "    bindchange=\"handleTreeSelect\"",
      "  />",
      "  <t-dropdown-item",
      "    label=\"选项最多八字树形三列\"",
      "    optionsLayout=\"tree\"",
      "    options=\"{{tripleColumnsTree.options}}\"",
      "    defaultValue=\"{{tripleColumnsTree.value}}\"",
      "    multiple",
      "  />",
      "</t-dropdown-menu>"
    ],
    "description": "TDesign DropdownMenu 组件"
  }
}